FileUtils_GTest/FileUtils.py
FileUtils_GTest/__init__.py
FileUtils_GTest-0.0.1.dist-info/LICENSE
FileUtils_GTest-0.0.1.dist-info/METADATA
FileUtils_GTest-0.0.1.dist-info/WHEEL
FileUtils_GTest-0.0.1.dist-info/top_level.txt
FileUtils_GTest-0.0.1.dist-info/RECORD
